{
    "movies" : [
        {
            "title" : "Stand by Me",
            "year" : "1986",
            "genre" : "Adventure, Comedy, Drama",
            "director" : "Rob Reiner",
            "imgURL" : "https://m.media-amazon.com/images/M/MV5BNGJkNTUwM2MtZWE2MS00YjNkLWE3MjktNWQwZDQxMDIyZWVmXkEyXkFqcGc@._V1_SX300.jpg"
        },
        {
            "title" : "The Shawshank Redemption",
            "year" : "1994",
            "genre" : "Drama",
            "director" : "Frank Darabont",
            "imgURL" : "https://m.media-amazon.com/images/M/MV5BMDAyY2FhYjctNDc5OS00MDNlLThiMGUtY2UxYWVkNGY2ZjljXkEyXkFqcGc@._V1_SX300.jpg"
        },
        {
            "title" : "Raiders of the Lost Ark",
            "year" : "1981",
            "genre" : "Action, Adventure",
            "director" : "Steven Spielberg",
            "imgURL" : "https://m.media-amazon.com/images/M/MV5BOGNhMjg2ZjgtYzk4Ni00MTViLTg1MmUtYzM2MDZiYjZlMmU3XkEyXkFqcGc@._V1_SX300.jpg"
        },
        {
            "title" : "Dune: Part One",
            "year" : "2021",
            "genre" : "Action, Adventure, Drama",
            "director" : "Denis Villeneuve",
            "imgURL" : "https://m.media-amazon.com/images/M/MV5BMDQ0NjgyN2YtNWViNS00YjA3LTkxNDktYzFkZTExZGMxZDkxXkEyXkFqcGdeQXVyODE5NzE3OTE@._V1_SX300.jpg"
        },
        {
            "title" : "Fight Club",
            "year" : "1999",
            "genre" : "Drama",
            "director" : "David Fincher",
            "imgURL" : "https://m.media-amazon.com/images/M/MV5BOTgyOGQ1NDItNGU3Ny00MjU3LTg2YWEtNmEyYjBiMjI1Y2M5XkEyXkFqcGc@._V1_SX300.jpg"
        },
        {
            "title" : "Donnie Darko",
            "year" : "2001",
            "genre" : "Drama, Mystery, Sci-Fi",
            "director" : "Richard Kelly",
            "imgURL" : "https://m.media-amazon.com/images/M/MV5BMWE3NTYzZmEtM2U5MS00MDZhLTk2ZTQtZTgzNjg0ZGQ5ZjM0XkEyXkFqcGc@._V1_SX300.jpg"
        },
        {
            "title" : "Ghostbusters",
            "year" : "1984",
            "genre" : "Action, Comedy, Fantasy",
            "director" : "Ivan Reitman",
            "imgURL" : "https://m.media-amazon.com/images/M/MV5BMGI0Yjg2ODAtNDYzNi00Njc2LTlkMmMtMmRmYWI5MDE4ZGRkXkEyXkFqcGc@._V1_SX300.jpg"
        },
        {
            "title" : "Halloween",
            "year" : "1978",
            "genre" : "Horror, Thriller",
            "director" : "John Carpenter",
            "imgURL" : "https://m.media-amazon.com/images/M/MV5BNzk1OGU2NmMtNTdhZC00NjdlLWE5YTMtZTQ0MGExZTQzOGQyXkEyXkFqcGdeQXVyMTQxNzMzNDI@._V1_SX300.jpg"
        },
        {
            "title" : "The Matrix",
            "year" : "1999",
            "genre" : "Action, Sci-Fi",
            "director" : "Larry Wachowski, Andy Wachowski",
            "imgURL" : "https://m.media-amazon.com/images/M/MV5BNzQzOTk3OTAtNDQ0Zi00ZTVkLWI0MTEtMDllZjNkYzNjNTc4L2ltYWdlXkEyXkFqcGdeQXVyNjU0OTQ0OTY@._V1_SX300.jpg"
        },
        {
            "title" : "Primer",
            "year" : "2004",
            "genre" : "Drama, Sci-Fi, Thriller",
            "director" : "Shane Carruth",
            "imgURL" : "https://m.media-amazon.com/images/M/MV5BZTRmZDlmNzUtNjM2NS00MjBjLWFmNjQtMTczMWNkZTdiOGZmXkEyXkFqcGc@._V1_SX300.jpg"
        }
    ]
}